arcade_airtable_api/__init__.py
arcade_airtable_api/moar/Airtable.json
arcade_airtable_api/moar/openapi.json
arcade_airtable_api/tools/__init__.py
arcade_airtable_api/tools/request_body_schemas.py
arcade_airtable_api/wrapper_tools/AddBaseCollaborator.json
arcade_airtable_api/wrapper_tools/AddCollaboratorToAirtableInterface.json
arcade_airtable_api/wrapper_tools/AddRecordComment.json
arcade_airtable_api/wrapper_tools/AddWorkspaceCollaborator.json
arcade_airtable_api/wrapper_tools/AirtableGetRecord.json
arcade_airtable_api/wrapper_tools/BatchManageEnterpriseUsers.json
arcade_airtable_api/wrapper_tools/BatchManageUserMembership.json
arcade_airtable_api/wrapper_tools/BatchMoveUserGroupsBetweenAccounts.json
arcade_airtable_api/wrapper_tools/BulkUpdateAirtable.json
arcade_airtable_api/wrapper_tools/CreateAirtableBase.json
arcade_airtable_api/wrapper_tools/CreateAirtableField.json
arcade_airtable_api/wrapper_tools/CreateAirtableRecords.json
arcade_airtable_api/wrapper_tools/CreateAirtableTable.json
arcade_airtable_api/wrapper_tools/CreateAirtableWebhook.json
arcade_airtable_api/wrapper_tools/CreateAirtableWorkspace.json
arcade_airtable_api/wrapper_tools/CreateAuditLogRequest.json
arcade_airtable_api/wrapper_tools/CreateDescendantEnterpriseAccount.json
arcade_airtable_api/wrapper_tools/CreateEdiscoveryExport.json
arcade_airtable_api/wrapper_tools/CreateScimGroup.json
arcade_airtable_api/wrapper_tools/CreateScimUser.json
arcade_airtable_api/wrapper_tools/DeleteAirtableBase.json
arcade_airtable_api/wrapper_tools/DeleteAirtableBlockInstallation.json
arcade_airtable_api/wrapper_tools/DeleteAirtableRecord.json
arcade_airtable_api/wrapper_tools/DeleteAirtableShare.json
arcade_airtable_api/wrapper_tools/DeleteAirtableView.json
arcade_airtable_api/wrapper_tools/DeleteAirtableWebhook.json
arcade_airtable_api/wrapper_tools/DeleteBaseInvite.json
arcade_airtable_api/wrapper_tools/DeleteCommentFromRecord.json
arcade_airtable_api/wrapper_tools/DeleteEnterpriseUser.json
arcade_airtable_api-4.0.0.dist-info/METADATA
arcade_airtable_api-4.0.0.dist-info/WHEEL
arcade_airtable_api-4.0.0.dist-info/entry_points.txt
arcade_airtable_api-4.0.0.dist-info/licenses/LICENSE
arcade_airtable_api-4.0.0.dist-info/RECORD
